studio_design_mcp/__init__.py
studio_design_mcp/__main__.py
studio_design_mcp/config.py
studio_design_mcp/server.py
studio_design_mcp/data/mobbin/apps_done.json
studio_design_mcp/data/mobbin/apps_seed.json
studio_design_mcp/data/mobbin/apps_skipped.json
studio_design_mcp/data/mobbin/catalog.json
studio_design_mcp/data/mobbin/screens_part1.json
studio_design_mcp/data/mobbin/screens_part2.json
studio_design_mcp/data/mobbin/screens_part3.json
studio_design_mcp/data/mobbin/screens_part4.json
studio_design_mcp/data/mobbin/screens_part5.json
studio_design_mcp/data/mobbin/screens_part6.json
studio_design_mcp/data/mobbin/screens_part7.json
studio_design_mcp/data/mobbin/screens_part8.json
studio_design_mcp/design_template/components/avatar.html
studio_design_mcp/design_template/components/badge.html
studio_design_mcp/design_template/components/button.html
studio_design_mcp/design_template/components/card.html
studio_design_mcp/design_template/components/chat-message.html
studio_design_mcp/design_template/components/checkbox.html
studio_design_mcp/design_template/components/chip.html
studio_design_mcp/design_template/components/citation.html
studio_design_mcp/design_template/components/desktop-composer.html
studio_design_mcp/design_template/components/dialog.html
studio_design_mcp/design_template/components/list-item.html
studio_design_mcp/design_template/components/radio.html
studio_design_mcp/design_template/components/switch.html
studio_design_mcp/design_template/components/textbox.html
studio_design_mcp/design_template/components/toast-notification.html
studio_design_mcp/design_template/pages/copilot-chat.html
studio_design_mcp/design_template/pages/copilot-discover.html
studio_design_mcp/design_template/pages/copilot-home.html
studio_design_mcp/studio_mcp_features/__init__.py
studio_design_mcp/studio_mcp_features/dribbble_headless_browser/searcher.py
studio_design_mcp/studio_mcp_features/dribbble_headless_browser/test_dribbble.py
studio_design_mcp-1.0.1.dist-info/METADATA
studio_design_mcp-1.0.1.dist-info/WHEEL
studio_design_mcp-1.0.1.dist-info/entry_points.txt
studio_design_mcp-1.0.1.dist-info/RECORD
