Metadata-Version: 2.4
Name: studio-design-mcp
Version: 1.0.1
Summary: Designer Studio MCP Server - A Model Context Protocol server for mobile UI inspiration via Mobbin
Requires-Python: <3.11,>=3.10
Requires-Dist: aiohttp
Requires-Dist: fastmcp
Requires-Dist: httpx
Requires-Dist: playwright
Requires-Dist: requests
